{
  "date": "2005-08-23",
  "paths": {
    "date_dir": "resultats-et-rapports/2005/08/2005-08-23",
    "date_html": "resultats-et-rapports/2005/08/2005-08-23/2005-08-23.html"
  },
  "missing": {
    "date_html": false,
    "reunion_dirs": [],
    "reunion_html": [],
    "course_files": []
  },
  "extras": {
    "reunion_dirs": [],
    "course_files": []
  },
  "expected": {
    "reunions_fr": [
      "R1-deauville",
      "R2-vincennes"
    ],
    "courses_by_reunion": {
      "R1-deauville": [
        "R1C1-prix-shadwell.html",
        "R1C2-prix-tanit.html",
        "R1C3-prix-minerve-shadwell.html",
        "R1C4-prix-de-lieurey-shadwell.html",
        "R1C5-prix-de-caumont-l-evente.html",
        "R1C6-prix-des-espoirs.html",
        "R1C7-prix-du-hoguenet.html"
      ],
      "R2-vincennes": [
        "R2C1-prix-shadwell.html",
        "R2C2-prix-tanit.html",
        "R2C3-prix-minerve-shadwell.html",
        "R2C4-prix-de-lieurey-shadwell.html",
        "R2C5-prix-de-caumont-l-evente.html",
        "R2C6-prix-des-espoirs.html",
        "R2C7-prix-du-hoguenet.html"
      ]
    }
  },
  "checked_at": "2025-11-13T01:37:19.131106Z"
}