{
  "date": "2016-02-02",
  "paths": {
    "date_dir": "resultats-et-rapports/2016/02/2016-02-02",
    "date_html": "resultats-et-rapports/2016/02/2016-02-02/2016-02-02.html"
  },
  "missing": {
    "date_html": false,
    "reunion_dirs": [],
    "reunion_html": [],
    "course_files": [
      "resultats-et-rapports/2016/02/2016-02-02/R1-vincennes/R1C1-prix-de-carcassonne.html",
      "resultats-et-rapports/2016/02/2016-02-02/R2-pau/R2C2-prix-de-vitteaux.html"
    ]
  },
  "extras": {
    "reunion_dirs": [],
    "course_files": []
  },
  "expected": {
    "reunions_fr": [
      "R1-vincennes",
      "R2-pau"
    ],
    "courses_by_reunion": {
      "R1-vincennes": [
        "R1C1-prix-de-carcassonne.html",
        "R1C2-prix-de-vitteaux.html",
        "R1C3-prix-de-vittel.html",
        "R1C4-prix-de-cholet.html",
        "R1C5-prix-de-laval.html",
        "R1C6-prix-d-ambert.html",
        "R1C7-prix-jean-et-andre-de-la-vaissiere.html",
        "R1C8-prix-de-sarlat.html"
      ],
      "R2-pau": [
        "R2C1-prix-de-carcassonne.html",
        "R2C2-prix-de-vitteaux.html",
        "R2C3-prix-de-vittel.html",
        "R2C4-prix-de-cholet.html",
        "R2C5-prix-de-laval.html",
        "R2C6-prix-d-ambert.html",
        "R2C7-prix-jean-et-andre-de-la-vaissiere.html",
        "R2C8-prix-de-sarlat.html"
      ]
    }
  },
  "checked_at": "2025-11-13T07:48:25.487434Z"
}