{
  "date": "2006-10-23",
  "paths": {
    "date_dir": "resultats-et-rapports/2006/10/2006-10-23",
    "date_html": "resultats-et-rapports/2006/10/2006-10-23/2006-10-23.html"
  },
  "missing": {
    "date_html": false,
    "reunion_dirs": [],
    "reunion_html": [],
    "course_files": [
      "resultats-et-rapports/2006/10/2006-10-23/R1-maisons-laffitte/R1C2-prix-d-eaubonne.html",
      "resultats-et-rapports/2006/10/2006-10-23/R1-maisons-laffitte/R1C3-prix-bagheera.html",
      "resultats-et-rapports/2006/10/2006-10-23/R1-maisons-laffitte/R1C4-prix-du-lieu-marmion.html",
      "resultats-et-rapports/2006/10/2006-10-23/R1-maisons-laffitte/R1C5-prix-biribi.html",
      "resultats-et-rapports/2006/10/2006-10-23/R1-maisons-laffitte/R1C6-prix-du-vexin.html",
      "resultats-et-rapports/2006/10/2006-10-23/R1-maisons-laffitte/R1C7-prix-du-lieu-manchon.html",
      "resultats-et-rapports/2006/10/2006-10-23/R2-angers/R2C1-prix-samourai.html"
    ]
  },
  "expected": {
    "reunions_fr": [
      "R1-maisons-laffitte",
      "R2-angers",
      "R3-enghien-soisy",
      "R21-zerace"
    ],
    "courses_by_reunion": {
      "R1-maisons-laffitte": [
        "R1C1-prix-samourai.html",
        "R1C2-prix-d-eaubonne.html",
        "R1C3-prix-bagheera.html",
        "R1C4-prix-du-lieu-marmion.html",
        "R1C5-prix-biribi.html",
        "R1C6-prix-du-vexin.html",
        "R1C7-prix-du-lieu-manchon.html"
      ],
      "R2-angers": [
        "R2C1-prix-samourai.html",
        "R2C2-prix-d-eaubonne.html",
        "R2C3-prix-bagheera.html",
        "R2C4-prix-du-lieu-marmion.html",
        "R2C5-prix-biribi.html",
        "R2C6-prix-du-vexin.html",
        "R2C7-prix-du-lieu-manchon.html"
      ],
      "R3-enghien-soisy": [
        "R3C1-prix-samourai.html",
        "R3C2-prix-d-eaubonne.html",
        "R3C3-prix-bagheera.html",
        "R3C4-prix-du-lieu-marmion.html",
        "R3C5-prix-biribi.html",
        "R3C6-prix-du-vexin.html",
        "R3C7-prix-du-lieu-manchon.html"
      ],
      "R21-zerace": [
        "R21C1-prix-samourai.html",
        "R21C2-prix-d-eaubonne.html",
        "R21C3-prix-bagheera.html",
        "R21C4-prix-du-lieu-marmion.html",
        "R21C5-prix-biribi.html",
        "R21C6-prix-du-vexin.html",
        "R21C7-prix-du-lieu-manchon.html"
      ]
    }
  },
  "checked_at": "2025-11-13T03:25:16.177199Z"
}